COPYING
COPYING.LESSER
MANIFEST.in
README.md
setup.cfg
setup.py
CoastProc/__init__.py
CoastProc/altiwave.py
CoastProc/documentation.py
CoastProc.egg-info/PKG-INFO
CoastProc.egg-info/SOURCES.txt
CoastProc.egg-info/dependency_links.txt
CoastProc.egg-info/requires.txt
CoastProc.egg-info/top_level.txt
CoastProc/Notebooks/dataset/.DS_Store
CoastProc/Notebooks/dataset/2010-YASI.csv
CoastProc/Notebooks/dataset/FraserDEM.csv
CoastProc/Notebooks/dataset/IMOSURLs.txt
CoastProc/Notebooks/dataset/IMOS_ANMN-NSW_W_20080124T210000Z_WAVEBAB_WAVERIDER_FV01_END-20151231T130000Z.nc
CoastProc/Notebooks/dataset/IMOS_ANMN-NSW_W_20150210T230000Z_WAVESYD_WAVERIDER_FV01_END-20171231T130000Z.nc
CoastProc/Notebooks/dataset/IMOS_NZ.txt
CoastProc/Notebooks/dataset/IMOS_YASI_east.txt
CoastProc/Notebooks/dataset/IMOS_YASI_west.txt
CoastProc/Notebooks/dataset/power18.csv
CoastProc/Notebooks/dataset/test_profiles.pkl
CoastProc/Notebooks/notebooks/CoastSat.ipynb
CoastProc/Notebooks/notebooks/IntroNotebook.ipynb
CoastProc/Notebooks/notebooks/Untitled.ipynb
CoastProc/Notebooks/notebooks/ex3.ipynb