Metadata-Version: 2.1
Name: CoastProc
Version: 0.0.3
Summary: Coastal Processes, Environments & Systems.
Home-page: https://github.com/TristanSalles/CoastProc
Author: Tristan Salles
Author-email: tristan.salles@sydney.edu.au
License: UNKNOWN
Platform: UNKNOWN
Classifier: Programming Language :: Python :: 3.3
Classifier: Programming Language :: Python :: 3.4
Classifier: Programming Language :: Python :: 3.5
Classifier: Programming Language :: Python :: 3.6
Requires-Python: >=3.3
